LICENSE
MANIFEST.in
README
requirements.txt
setup.py
doc/_build/html/.buildinfo
doc/_build/html/extract.html
doc/_build/html/genindex.html
doc/_build/html/index.html
doc/_build/html/modules.html
doc/_build/html/objects.inv
doc/_build/html/py-modindex.html
doc/_build/html/search.html
doc/_build/html/searchindex.js
doc/_build/html/sub.html
doc/_build/html/_modules/extract.html
doc/_build/html/_modules/index.html
doc/_build/html/_modules/sub/m1.html
doc/_build/html/_modules/sub/m2.html
doc/_build/html/_sources/extract.rst.txt
doc/_build/html/_sources/index.rst.txt
doc/_build/html/_sources/modules.rst.txt
doc/_build/html/_sources/sub.rst.txt
doc/_build/html/_sources/doc/conf.rst.txt
doc/_build/html/_sources/doc/modules.rst.txt
doc/_build/html/_static/ajax-loader.gif
doc/_build/html/_static/basic.css
doc/_build/html/_static/classic.css
doc/_build/html/_static/comment-bright.png
doc/_build/html/_static/comment-close.png
doc/_build/html/_static/comment.png
doc/_build/html/_static/doctools.js
doc/_build/html/_static/documentation_options.js
doc/_build/html/_static/down-pressed.png
doc/_build/html/_static/down.png
doc/_build/html/_static/file.png
doc/_build/html/_static/jquery-3.2.1.js
doc/_build/html/_static/jquery.js
doc/_build/html/_static/minus.png
doc/_build/html/_static/plus.png
doc/_build/html/_static/pygments.css
doc/_build/html/_static/searchtools.js
doc/_build/html/_static/sidebar.js
doc/_build/html/_static/underscore-1.3.1.js
doc/_build/html/_static/underscore.js
doc/_build/html/_static/up-pressed.png
doc/_build/html/_static/up.png
doc/_build/html/_static/websupport.js
doc/_build/html/doc/conf.html
doc/_build/html/doc/modules.html
src/extract
src/ECSU_Midterm_Proj.egg-info/PKG-INFO
src/ECSU_Midterm_Proj.egg-info/SOURCES.txt
src/ECSU_Midterm_Proj.egg-info/dependency_links.txt
src/ECSU_Midterm_Proj.egg-info/requires.txt
src/ECSU_Midterm_Proj.egg-info/top_level.txt
src/myFormat/__init__.py
src/myFormat/extract.py
src/myFormat/other/midterm.txt
src/myFormat/sub/__init__.py
src/myFormat/sub/m1.py
src/myFormat/sub/m2.py
test/test_m1.py
test/test_m2.py