Metadata-Version: 1.1
Name: ECSU-Midterm-Proj
Version: 0.2
Summary: Extracts HTML data with python regex and convert the data to a csv file
Home-page: https://github.com/dislbenn
Author: Disaiah Bennett
Author-email: dlbennett365@ecsu.edu
License: Creative Commons Attribution-Noncommercial-Share Alike license
Platform: UNKNOWN
Classifier: Development Status :: 4 - Beta
Classifier: Environment :: X11 Applications :: GTK
Classifier: Intended Audience :: End Users/Desktop
Classifier: Intended Audience :: Developers
Classifier: License :: OSI Approved :: GNU General Public License (GPL)
Classifier: Operating System :: POSIX :: Linux
Classifier: Programming Language :: Python
Classifier: Topic :: Desktop Environment
Classifier: Topic :: Text Processing :: Fonts
